isrmltoolkit/__init__.py
isrmltoolkit/compare_columns.py
isrmltoolkit/datetime.py
isrmltoolkit/my_analysis.py
isrmltoolkit/outliers.py
isrmltoolkit/winsorization.py
isrmltoolkit-0.1.15.dist-info/licenses/LICENSE
isrmltoolkit-0.1.15.dist-info/METADATA
isrmltoolkit-0.1.15.dist-info/WHEEL
isrmltoolkit-0.1.15.dist-info/top_level.txt
isrmltoolkit-0.1.15.dist-info/RECORD
