Metadata-Version: 2.4
Name: isrmltoolkit
Version: 0.1.15
Summary: Funciones y utilidades útiles para proyectos de Machine Learning
Home-page: https://github.com/Israelamat/pip_install
Author: Isra
Author-email: ismael@email.com
Classifier: Programming Language :: Python :: 3
Classifier: Operating System :: OS Independent
Requires-Python: >=3.6
License-File: LICENSE
Requires-Dist: pandas>=1.0.0
Requires-Dist: scikit-learn>=0.24
Requires-Dist: scipy>=1.5
Requires-Dist: matplotlib>=3.0
Requires-Dist: seaborn>=0.10
Dynamic: author
Dynamic: author-email
Dynamic: classifier
Dynamic: home-page
Dynamic: license-file
Dynamic: requires-dist
Dynamic: requires-python
Dynamic: summary
